config/__init__.py
config/aggregators.py
config/pairs.py
config/slippage.py
src/__init__.py
src/api.py
src/benchmark.py
src/tool_storage.py
types_custom/__init__.py
types_custom/apiKeys.py
types_custom/apiRequests.py
types_custom/dex.py
types_custom/tokens.py
utils/__init__.py
utils/array_builder.py
propeller_benchmark-1.0.7.dist-info/METADATA
propeller_benchmark-1.0.7.dist-info/WHEEL
propeller_benchmark-1.0.7.dist-info/top_level.txt
propeller_benchmark-1.0.7.dist-info/RECORD
